inspinet_asymetric_encryption/__init__.py
inspinet_asymetric_encryption/decrypt.py
inspinet_asymetric_encryption/encrypt.py
inspinet_asymetric_encryption-0.0.1.dist-info/METADATA
inspinet_asymetric_encryption-0.0.1.dist-info/WHEEL
inspinet_asymetric_encryption-0.0.1.dist-info/licenses/LICENSE
inspinet_asymetric_encryption-0.0.1.dist-info/RECORD
