Metadata-Version: 2.3
Name: inspinet_asymetric_encryption
Version: 0.0.1
Summary: Asymetric encryption using public/private key pairs
Project-URL: Buy_Me_A_Coffee, https://www.buymeacoffee.com/inspinet
Project-URL: Homepage, https://github.com/inspinet/inspinet_asymetric_encryption
Project-URL: Issues, https://github.com/inspinet/inspinet_asymetric_encryption/issues
Author-email: Sebastian Butowski <contact@inspinet.co.uk>
License-File: LICENSE
Classifier: License :: OSI Approved :: MIT License
Classifier: Operating System :: OS Independent
Classifier: Programming Language :: Python :: 3
Requires-Python: >=3.8
